README.md
setup.py
coin_numberportability/__init__.py
coin_numberportability/config.py
coin_numberportability/domain.py
coin_numberportability/receiver.py
coin_numberportability/securityservice.py
coin_numberportability/sender.py
coin_numberportability/utils.py
coin_numberportability.egg-info/PKG-INFO
coin_numberportability.egg-info/SOURCES.txt
coin_numberportability.egg-info/dependency_links.txt
coin_numberportability.egg-info/not-zip-safe
coin_numberportability.egg-info/requires.txt
coin_numberportability.egg-info/top_level.txt
coin_numberportability/messages/__init__.py
coin_numberportability/messages/message.py
coin_numberportability/messages/message_response.py
coin_numberportability/messages/cancel/__init__.py
coin_numberportability/messages/cancel/cancel.py
coin_numberportability/messages/cancel/cancel_body.py
coin_numberportability/messages/cancel/cancel_builder.py
coin_numberportability/messages/cancel/cancel_message.py
coin_numberportability/messages/common/__init__.py
coin_numberportability/messages/common/confirmation_message.py
coin_numberportability/messages/common/customer_info.py
coin_numberportability/messages/common/enum_profile_seq.py
coin_numberportability/messages/common/enum_repeats.py
coin_numberportability/messages/common/enum_repeats_builder.py
coin_numberportability/messages/common/error_message.py
coin_numberportability/messages/common/header.py
coin_numberportability/messages/common/header_creator.py
coin_numberportability/messages/common/number_series.py
coin_numberportability/messages/common/receiver.py
coin_numberportability/messages/common/sender.py
coin_numberportability/messages/deactivation/__init__.py
coin_numberportability/messages/deactivation/deactivation.py
coin_numberportability/messages/deactivation/deactivation_body.py
coin_numberportability/messages/deactivation/deactivation_builder.py
coin_numberportability/messages/deactivation/deactivation_message.py
coin_numberportability/messages/deactivation/deactivation_repeats.py
coin_numberportability/messages/deactivation/deactivation_seq.py
coin_numberportability/messages/portingperformed/__init__.py
coin_numberportability/messages/portingperformed/porting_performed.py
coin_numberportability/messages/portingperformed/porting_performed_body.py
