Metadata-Version: 1.2
Name: coin-numberportability
Version: 0.1.0
Summary: SDK for VereningingCOIN's numberportability api
Home-page: https://gitlab.com/verenigingcoin-public/number-portability-sdk
Author: VereninginCOIN
Author-email: devops@coin.nl
License: MIT
Keywords: COIN,Numberportability,TELECOM,SDK
Platform: any
Classifier: Development Status :: 4 - Beta
Classifier: Intended Audience :: Developers
Classifier: Topic :: Software Development :: Libraries
Classifier: License :: OSI Approved :: MIT License
Classifier: Programming Language :: Python :: 3.6
Requires-Python: >=3.6
